pychats/__init__.py
pychats/chats/__init__.py
pychats/chats/chatlogs.py
pychats/chats/conversations.py
pychats/chats/messages.py
pychats/chats/people.py
pychats/parse/__init__.py
pychats/parse/facebook.py
pychats-2.2.0.dist-info/DESCRIPTION.rst
pychats-2.2.0.dist-info/METADATA
pychats-2.2.0.dist-info/RECORD
pychats-2.2.0.dist-info/WHEEL
pychats-2.2.0.dist-info/metadata.json
pychats-2.2.0.dist-info/top_level.txt
